AUTHORS.rst
CONTRIBUTING.rst
HISTORY.rst
LICENSE
MANIFEST.in
README.rst
setup.cfg
setup.py
docs/Makefile
docs/authors.rst
docs/conf.py
docs/contributing.rst
docs/history.rst
docs/index.rst
docs/installation.rst
docs/make.bat
docs/readme.rst
docs/usage.rst
test_earlybirds/__init__.py
test_earlybirds/app.py
test_earlybirds/cli.py
test_earlybirds/model.py
test_earlybirds.egg-info/PKG-INFO
test_earlybirds.egg-info/SOURCES.txt
test_earlybirds.egg-info/dependency_links.txt
test_earlybirds.egg-info/entry_points.txt
test_earlybirds.egg-info/not-zip-safe
test_earlybirds.egg-info/requires.txt
test_earlybirds.egg-info/top_level.txt
tests/test_model.py
tests/test_test_earlybirds.py