Metadata-Version: 1.1
Name: test-earlybirds
Version: 0.1.5
Summary: technical test for Earlybirds
Home-page: https://github.com/simonmeoni/test_earlybirds
Author: Simon Meoni
Author-email: simonmeoni@aol.com
License: Apache Software License 2.0
Keywords: test_earlybirds
Platform: UNKNOWN
Classifier: Development Status :: 2 - Pre-Alpha
Classifier: Intended Audience :: Developers
Classifier: License :: OSI Approved :: Apache Software License
Classifier: Natural Language :: English
Classifier: Programming Language :: Python :: 3
Classifier: Programming Language :: Python :: 3.4
Classifier: Programming Language :: Python :: 3.5
Classifier: Programming Language :: Python :: 3.6
Classifier: Programming Language :: Python :: 3.7
